ft_tomato_clock-0.1.1.dist-info/licenses/LICENSE
tomato_clock/__init__.py
tomato_clock/cli.py
ft_tomato_clock-0.1.1.dist-info/METADATA
ft_tomato_clock-0.1.1.dist-info/WHEEL
ft_tomato_clock-0.1.1.dist-info/entry_points.txt
ft_tomato_clock-0.1.1.dist-info/top_level.txt
ft_tomato_clock-0.1.1.dist-info/RECORD
