Metadata-Version: 2.4
Name: ft_tomato_clock
Version: 0.1.1
Summary: A simple Pomodoro timer for command line with stats tracking.
Author-email: Iwbhiwnd <Iwbhiwnd@gmail.com>
License: MIT License
Classifier: Programming Language :: Python :: 3
Classifier: License :: OSI Approved :: MIT License
Classifier: Operating System :: OS Independent
Classifier: Environment :: Console
Classifier: Topic :: Utilities
Requires-Python: >=3.7
License-File: LICENSE
Requires-Dist: plyer>=2.0
Dynamic: license-file
